legit_api_client/__init__.py
legit_api_client/api_client.py
legit_api_client/api_response.py
legit_api_client/configuration.py
legit_api_client/exceptions.py
legit_api_client/py.typed
legit_api_client/rest.py
legit_api_client/api/__init__.py
legit_api_client/api/amazon_ecr_key_integration_api.py
legit_api_client/api/amazon_ecr_role_integration_api.py
legit_api_client/api/brokers_api.py
legit_api_client/api/cloud_instances_api.py
legit_api_client/api/collaborators_api.py
legit_api_client/api/compliance_api.py
legit_api_client/api/container_images_api.py
legit_api_client/api/custom_fields_api.py
legit_api_client/api/dependencies_v2_api.py
legit_api_client/api/integrations_api.py
legit_api_client/api/issues_api.py
legit_api_client/api/issues_v2_api.py
legit_api_client/api/models_api.py
legit_api_client/api/policies_api.py
legit_api_client/api/product_units_api.py
legit_api_client/api/repositories_api.py
legit_api_client/api/repository_groups_api.py
legit_api_client/api/saved_queries_api.py
legit_api_client/api/sdlc_assets_api.py
legit_api_client/api/tags_api.py
legit_api_client/api/workspaces_api.py
legit_api_client/models/__init__.py
legit_api_client/models/add_issue_comment_dto.py
legit_api_client/models/ai_model_reputation_dto.py
legit_api_client/models/ai_secret_validation_result.py
legit_api_client/models/amazon_ecr_key_integration_create_dto.py
legit_api_client/models/amazon_ecr_key_integration_edit_dto.py
legit_api_client/models/amazon_ecr_role_integration_create_dto.py
legit_api_client/models/amazon_ecr_role_integration_edit_dto.py
legit_api_client/models/apply_bulk_workspace_operation_dto.py
legit_api_client/models/apply_bulk_workspace_roles_operation_dto.py
legit_api_client/models/asset_connection_dto.py
legit_api_client/models/automatic_check_dto.py
legit_api_client/models/aws_region.py
legit_api_client/models/azure_container_registry_integration_create_dto.py
legit_api_client/models/azure_container_registry_integration_edit_dto.py
legit_api_client-1.1.4639.dist-info/METADATA
legit_api_client-1.1.4639.dist-info/WHEEL
legit_api_client-1.1.4639.dist-info/top_level.txt
legit_api_client-1.1.4639.dist-info/RECORD
